LICENCE
README.md
setup.py
yutool/__init__.py
yutool.egg-info/PKG-INFO
yutool.egg-info/SOURCES.txt
yutool.egg-info/dependency_links.txt
yutool.egg-info/top_level.txt