Metadata-Version: 2.1
Name: yutool
Version: 0.1.0
Summary: tools for python
Home-page: https://github.com/kbrownehs18/yutool
Author: Piggy
Author-email: scnjl@qq.com
License: MulanPubL-2.0
Platform: UNKNOWN
Requires-Python: >=3.6
License-File: LICENCE
